{
  "setting": {
    "es6": true,
    "postcss": true,
    "minified": true,
    "uglifyFileName": false,
    "enhance": true,
    "packNpmManually": false,
    "babelSetting": {
      "ignore": [],
      "disablePlugins": [],
      "outputPath": ""
    },
    "useCompilerPlugins": false,
    "minifyWXML": true,
    "urlCheck": false,
    "es6Enhance": true
  },
  "compileType": "miniprogram",
  "simulatorPluginLibVersion": {},
  "packOptions": {
    "ignore": [],
    "include": []
  },
  "appid": "wx4768ffec905b8f6c",
  "editorSetting": {}
}